armadilloml/__init__.py
armadilloml/api_client/__init__.py
armadilloml/api_client/exceptions.py
armadilloml/api_client/types.py
armadilloml/cli.py
armadilloml/serving.py
armadilloml/templates/examples/transformers/Dockerfile
armadilloml/templates/examples/transformers/app.py
armadilloml/templates/examples/transformers/requirements.txt
armadilloml/templates/project-template/.dockerignore
armadilloml/templates/project-template/.gcloudignore
armadilloml/templates/project-template/.gitattributes
armadilloml/templates/project-template/.github/workflows/cloud-run.yml
armadilloml/templates/project-template/.gitignore
armadilloml/templates/project-template/Dockerfile
armadilloml/templates/project-template/README.md
armadilloml/templates/project-template/app.py
armadilloml/templates/project-template/armadillo.json
armadilloml/templates/project-template/requirements.txt
armadilloml/templating.py
armadilloml/utils.py
armadilloml-0.1.17.dist-info/entry_points.txt
armadilloml-0.1.17.dist-info/WHEEL
armadilloml-0.1.17.dist-info/METADATA
armadilloml-0.1.17.dist-info/RECORD
