Metadata-Version: 2.1
Name: armadilloml
Version: 0.1.17
Summary: 
Author: Max Davish
Author-email: mdavish@yext.com
Requires-Python: >=3.7,<4.0
Classifier: Programming Language :: Python :: 3
Classifier: Programming Language :: Python :: 3.10
Classifier: Programming Language :: Python :: 3.7
Classifier: Programming Language :: Python :: 3.8
Classifier: Programming Language :: Python :: 3.9
Requires-Dist: Flask (>=2.1.1,<3.0.0)
Requires-Dist: GitPython (>=3.1.27,<4.0.0)
Requires-Dist: PyGithub (>=1.55,<2.0)
Requires-Dist: click (>=8.0.4,<9.0.0)
Requires-Dist: pydantic (>=1.9.0,<2.0.0)
Requires-Dist: requests (>=2.27.1,<3.0.0)
Requires-Dist: rich (>=12.0.1,<13.0.0)
Requires-Dist: rich-click (>=1.2.1,<2.0.0)
